tabledetect/__init__.py
tabledetect/tabledetect.py
tabledetect/helpers/__init__.py
tabledetect/helpers/boundigbox_to_cropped_image.py
tabledetect/helpers/download.py
tabledetect/helpers/yolo_to_boundingbox.py
tabledetect/resources/examples/2007-01404285-p2.png
tabledetect/resources/examples/2007-02501625-p3.png
tabledetect/resources/examples/2008-75500021-p4.png
tabledetect/resources/examples/2008-75500021-p8.png
tabledetect/resources/examples/2020-76400425-p1.png
tabledetect-0.3.0.dist-info/LICENSE
tabledetect-0.3.0.dist-info/WHEEL
tabledetect-0.3.0.dist-info/METADATA
tabledetect-0.3.0.dist-info/RECORD
